jspr/__init__.py
jspr/__main__.py
jspr/kernel.py
jspr/kernel_test.py
jspr/kws.py
jspr/kws_test.py
jspr/lang.py
jspr/lang_test.py
jspr/main.py
jspr/mod.py
jspr/runtime.py
jspr/util.py
jspr-0.1.1.dist-info/entry_points.txt
jspr-0.1.1.dist-info/WHEEL
jspr-0.1.1.dist-info/METADATA
jspr-0.1.1.dist-info/RECORD
