Metadata-Version: 2.1
Name: jspr
Version: 0.1.1
Summary: A JSON Processor
Author: vector-of-bool
Author-email: vectorofbool@gmail.com
Requires-Python: >=3.6,<4.0
Classifier: Programming Language :: Python :: 3
Classifier: Programming Language :: Python :: 3.10
Classifier: Programming Language :: Python :: 3.6
Classifier: Programming Language :: Python :: 3.7
Classifier: Programming Language :: Python :: 3.8
Classifier: Programming Language :: Python :: 3.9
Requires-Dist: typing-extensions (>=4.0.1,<5.0.0)
